data/__init__.py
data/audio.mp3
data/chipichipi.mp4
data/33/0.txt
data/33/1.txt
data/33/10.txt
data/33/100.txt
data/33/101.txt
data/33/102.txt
data/33/103.txt
data/33/104.txt
data/33/105.txt
data/33/106.txt
data/33/107.txt
data/33/108.txt
data/33/109.txt
data/33/11.txt
data/33/110.txt
data/33/111.txt
data/33/112.txt
data/33/113.txt
data/33/114.txt
data/33/115.txt
data/33/116.txt
data/33/117.txt
data/33/118.txt
data/33/119.txt
data/33/12.txt
data/33/120.txt
data/33/121.txt
data/33/122.txt
data/33/123.txt
data/33/124.txt
data/33/125.txt
data/33/126.txt
data/33/127.txt
data/33/128.txt
data/33/129.txt
data/33/13.txt
data/33/130.txt
data/33/131.txt
data/33/132.txt
data/33/133.txt
data/33/134.txt
data/33/135.txt
data/33/136.txt
data/33/137.txt
data/33/138.txt
data/33/139.txt
data/33/14.txt
data/33/140.txt
data/33/141.txt
data/33/142.txt
data/33/143.txt
data/33/144.txt
data/33/145.txt
data/33/146.txt
data/33/147.txt
data/33/148.txt
data/33/149.txt
data/33/15.txt
data/33/150.txt
data/33/151.txt
data/33/152.txt
data/33/153.txt
data/33/154.txt
data/33/155.txt
data/33/156.txt
data/33/157.txt
data/33/158.txt
data/33/159.txt
data/33/16.txt
data/33/160.txt
data/33/161.txt
data/33/162.txt
data/33/163.txt
data/33/164.txt
data/33/165.txt
data/33/166.txt
data/33/167.txt
data/33/168.txt
data/33/169.txt
data/33/17.txt
data/33/170.txt
data/33/171.txt
data/33/172.txt
data/33/173.txt
data/33/174.txt
data/33/175.txt
data/33/176.txt
data/33/177.txt
data/33/178.txt
data/33/179.txt
data/33/18.txt
data/33/180.txt
data/33/181.txt
data/33/182.txt
data/33/183.txt
data/33/184.txt
data/33/185.txt
data/33/186.txt
data/33/187.txt
data/33/188.txt
data/33/189.txt
data/33/19.txt
data/33/190.txt
data/33/191.txt
data/33/192.txt
data/33/193.txt
data/33/194.txt
data/33/195.txt
data/33/196.txt
data/33/197.txt
data/33/198.txt
data/33/199.txt
data/33/2.txt
data/33/20.txt
data/33/200.txt
data/33/201.txt
data/33/202.txt
data/33/203.txt
data/33/204.txt
data/33/205.txt
data/33/206.txt
data/33/207.txt
chipi_chipi-1.0.2.dist-info/LICENSE.txt
chipi_chipi-1.0.2.dist-info/METADATA
chipi_chipi-1.0.2.dist-info/WHEEL
chipi_chipi-1.0.2.dist-info/entry_points.txt
chipi_chipi-1.0.2.dist-info/top_level.txt
chipi_chipi-1.0.2.dist-info/RECORD
